<?xml version="1.0" encoding="UTF-8"?>
<Entities
 majorVersion="9"
 minorVersion="2"
 universal="password">
    <ApplicationKeys>
        <ApplicationKey
         clientName=""
         description=""
         documentationContent=""
         expirationDate="2023-01-30T18:30:00.000Z"
         homeMashup=""
         ipWhitelist=""
         keyId=""
         name="Kepware.AppKey"
         projectName="ThingWorx.Demo.Project"
         tags=""
         userNameReference="Administrator">
            <avatar></avatar>
            <DesignTimePermissions>
                <Create></Create>
                <Read></Read>
                <Update></Update>
                <Delete></Delete>
                <Metadata></Metadata>
            </DesignTimePermissions>
            <RunTimePermissions></RunTimePermissions>
            <VisibilityPermissions>
                <Visibility></Visibility>
            </VisibilityPermissions>
            <ConfigurationTableDefinitions></ConfigurationTableDefinitions>
            <ConfigurationTables></ConfigurationTables>
        </ApplicationKey>
    </ApplicationKeys>
</Entities>
