<?xml version="1.0" encoding="UTF-8"?>
<Entities
 majorVersion="9"
 minorVersion="3"
 universal="password">
    <ThingTemplates>
        <ThingTemplate
         baseThingTemplate="GenericThing"
         description=""
         documentationContent=""
         effectiveThingPackage="ConfiguredThing"
         homeMashup=""
         inheritedValueStream=""
         name="47364.JAE.ThingTemplate"
         projectName="ITC.Training.47364.GIMS.Project"
         tags=""
         thingPackage=""
         valueStream="">
            <avatar></avatar>
            <DesignTimePermissions>
                <Create></Create>
                <Read></Read>
                <Update></Update>
                <Delete></Delete>
                <Metadata></Metadata>
            </DesignTimePermissions>
            <RunTimePermissions></RunTimePermissions>
            <VisibilityPermissions>
                <Visibility></Visibility>
            </VisibilityPermissions>
            <ConfigurationTableDefinitions></ConfigurationTableDefinitions>
            <ConfigurationTables></ConfigurationTables>
            <PropertyBindings></PropertyBindings>
            <RemotePropertyBindings></RemotePropertyBindings>
            <RemoteServiceBindings></RemoteServiceBindings>
            <RemoteEventBindings></RemoteEventBindings>
            <AlertConfigurations></AlertConfigurations>
            <ThingShape>
                <PropertyDefinitions></PropertyDefinitions>
                <ServiceDefinitions></ServiceDefinitions>
                <EventDefinitions></EventDefinitions>
                <ServiceMappings></ServiceMappings>
                <ServiceImplementations></ServiceImplementations>
                <Subscriptions></Subscriptions>
            </ThingShape>
            <ImplementedShapes>
                <ImplementedShape
                 name="47364.JAE.ThingShape"
                 type="ThingShape"></ImplementedShape>
            </ImplementedShapes>
            <SharedConfigurationTables></SharedConfigurationTables>
            <InstanceDesignTimePermissions>
                <Create></Create>
                <Read></Read>
                <Update></Update>
                <Delete></Delete>
                <Metadata></Metadata>
            </InstanceDesignTimePermissions>
            <InstanceRunTimePermissions></InstanceRunTimePermissions>
            <InstanceVisibilityPermissions>
                <Visibility></Visibility>
            </InstanceVisibilityPermissions>
        </ThingTemplate>
    </ThingTemplates>
</Entities>
